<?xml version="1.0"?>
<election_record xmlns="http://dca.tufts.edu/aas" xmlns:xsi="http://www.w3.org/2001/XMLSchema-instance" label="Maryland 1794 House of Delegates, Baltimore County" type="General" iteration="First Ballot" date="1794-10" election_id="md.delegate.baltimore.county.1794" handle="10427/27436" xsi:schemaLocation="http://dca.tufts.edu/aas http://dca.tufts.edu/schema/aas/electionRecord.xsd">
	<office name="House of Delegates" office_id="ON063" scope="State">
		<role title="Delegate" scope="County">
			<ballot>
				<candidate name="Charles Ridgely" name_id="RC0020" affiliation="Federalist" affiliation_id="A01" candidate_num="1"><note resp="Philip Lampi">Elected.</note></candidate>
				<candidate name="John T. Worthington" name_id="WJ0162" affiliation="null" affiliation_id="null" candidate_num="2"><note resp="Philip Lampi">Elected.</note></candidate>
				<candidate name="Charles Ridgely of William" name_id="RC0025" affiliation="null" affiliation_id="null" candidate_num="3"><note resp="Philip Lampi">Elected.</note></candidate>
				<candidate name="Elijah Merryman" name_id="ME0021" affiliation="null" affiliation_id="null" candidate_num="4"><note resp="Philip Lampi">Elected.</note></candidate>
			</ballot>
			<overview status="Version 1.0" modified="2008-03-26">
				<candidate_summary candidate_ref="1" vote_total="798" resp="Philip Lampi"/>
				<candidate_summary candidate_ref="2" vote_total="755" resp="Philip Lampi"/>
				<candidate_summary candidate_ref="3" vote_total="738" resp="Philip Lampi"/>
				<candidate_summary candidate_ref="4" vote_total="598" resp="Philip Lampi"/>
				<reference type="page_image" urn="tufts:central:dca:MS115:MS115.001.DO.02176" resp="Philip Lampi"/>
			</overview>
			<admin_unit type="State" name="Maryland" geog_id="mds">
				<sub_unit type="County" name="Baltimore" geog_id="mds_baltimore">
					<result candidate_ref="1" vote="798" resp="Philip Lampi"/>
					<result candidate_ref="2" vote="755" resp="Philip Lampi"/>
					<result candidate_ref="3" vote="738" resp="Philip Lampi"/>
					<result candidate_ref="4" vote="598" resp="Philip Lampi"/>
					<reference type="page_image" urn="tufts:central:dca:MS115:MS115.001.DO.02176" resp="Philip Lampi"/>
				</sub_unit>
			</admin_unit>
		</role>
	</office>
	<reference type="citation" resp="Philip Lampi" urn="tufts:central:dca:MS115:MS115.001.DO.02176">Baltimore Daily Intelligencer (Baltimore, MD).  October 10, 1794.</reference>
</election_record>
