<?xml version="1.0"?>
<election_record label="New York 1824 State Senate, District 2" type="General" iteration="First Ballot" date="1824" election_id="ny.statesenate2.1824" handle="10427/31427" xmlns="http://dca.tufts.edu/aas" xmlns:xsi="http://www.w3.org/2001/XMLSchema-instance" xsi:schemaLocation="http://dca.tufts.edu/aas http://dca.tufts.edu/schema/aas/electionRecord.xsd">
	<office name="State Senate" office_id="ON109" scope="State">
		<role title="State Senator" scope="District">
			<ballot>
				<candidate name="Peter S. Van Orden" name_id="VP0038" affiliation="Clintonian/Federalist" affiliation_id="A05" candidate_num="1"/>
				<candidate name="Wells Lake" name_id="LW0111" affiliation="Bucktail" affiliation_id="A06" candidate_num="2"/>
				<candidate name="Alfred S. Pell" name_id="PA0068" affiliation="null" affiliation_id="null" candidate_num="3"/>
				<candidate name="Samuel S. Van Orden" name_id="VS0014" affiliation="null" affiliation_id="null" candidate_num="4"/>
				<candidate name="Walter Case" name_id="CW0169" affiliation="null" affiliation_id="null" candidate_num="5"/>
				<candidate name="Peter R. Livingston" name_id="LP0036" affiliation="null" affiliation_id="null" candidate_num="6"/>
				<candidate name="John White" name_id="WJ0590" affiliation="null" affiliation_id="null" candidate_num="7"/>
				<candidate name="Job Hoyt" name_id="HJ0613" affiliation="null" affiliation_id="null" candidate_num="8"/>
				<candidate name="Abraham Depew" name_id="DA0051" affiliation="null" affiliation_id="null" candidate_num="9"/>
				<candidate name="James Tamage" name_id="TJ0241" affiliation="null" affiliation_id="null" candidate_num="10"/>
				<candidate name="Thomas Smith" name_id="ST0190" affiliation="null" affiliation_id="null" candidate_num="11"/>
				<candidate name="John Feeks" name_id="FJ0261" affiliation="null" affiliation_id="null" candidate_num="12"/>
				<candidate name="Samuel Wilkin" name_id="WS0132" affiliation="null" affiliation_id="null" candidate_num="13"/>
				<candidate name="Samuel Weed" name_id="WS0137" affiliation="null" affiliation_id="null" candidate_num="14"/>
				<candidate name="Amzi L. Bell" name_id="BA0114" affiliation="null" affiliation_id="null" candidate_num="15"/>
			</ballot>
			<overview status="Version 0.5" modified="2012-01-17">
				<candidate_summary candidate_ref="1" vote_total="11011" resp="Philip Lampi"/>
				<candidate_summary candidate_ref="2" vote_total="11009" resp="Philip Lampi"/>
				<candidate_summary candidate_ref="3" vote_total="12" resp="Philip Lampi"/>
				<candidate_summary candidate_ref="4" vote_total="3" resp="Philip Lampi"/>
				<candidate_summary candidate_ref="5" vote_total="1" resp="Philip Lampi"/>
				<candidate_summary candidate_ref="6" vote_total="1" resp="Philip Lampi"/>
				<candidate_summary candidate_ref="7" vote_total="1" resp="Philip Lampi"/>
				<candidate_summary candidate_ref="8" vote_total="1" resp="Philip Lampi"/>
				<candidate_summary candidate_ref="9" vote_total="1" resp="Philip Lampi"/>
				<candidate_summary candidate_ref="10" vote_total="1" resp="Philip Lampi"/>
				<candidate_summary candidate_ref="11" vote_total="1" resp="Philip Lampi"/>
				<candidate_summary candidate_ref="12" vote_total="1" resp="Philip Lampi"/>
				<candidate_summary candidate_ref="13" vote_total="1" resp="Philip Lampi"/>
				<candidate_summary candidate_ref="14" vote_total="1" resp="Philip Lampi"/>
				<candidate_summary candidate_ref="15" vote_total="1" resp="Philip Lampi"/>
				<reference type="page_image" urn="tufts:central:dca:MS115:MS115.001.DO.04733" resp="Philip Lampi"/>
				<note resp="Philip Lampi">"Van Orden was the People's Candidate."  The New-York Statesman (Albany, NY).  November 5, 1824.</note>
			</overview>
			<admin_unit type="State" name="New York" geog_id="null">
				<sub_unit type="District" name="Two" geog_id="null">
					<result candidate_ref="1" vote="11011" resp="Philip Lampi"/>
					<result candidate_ref="2" vote="11009" resp="Philip Lampi"/>
					<result candidate_ref="3" vote="12" resp="Philip Lampi"/>
					<result candidate_ref="4" vote="3" resp="Philip Lampi"/>
					<result candidate_ref="5" vote="1" resp="Philip Lampi"/>
					<result candidate_ref="6" vote="1" resp="Philip Lampi"/>
					<result candidate_ref="7" vote="1" resp="Philip Lampi"/>
					<result candidate_ref="8" vote="1" resp="Philip Lampi"/>
					<result candidate_ref="9" vote="1" resp="Philip Lampi"/>
					<result candidate_ref="10" vote="1" resp="Philip Lampi"/>
					<result candidate_ref="11" vote="1" resp="Philip Lampi"/>
					<result candidate_ref="12" vote="1" resp="Philip Lampi"/>
					<result candidate_ref="13" vote="1" resp="Philip Lampi"/>
					<result candidate_ref="14" vote="1" resp="Philip Lampi"/>
					<result candidate_ref="15" vote="1" resp="Philip Lampi"/>
					<sub_unit type="County" name="Dutchess" geog_id="null">
						<result candidate_ref="1" vote="3646" resp="Philip Lampi"/>
						<result candidate_ref="2" vote="3183" resp="Philip Lampi"/>
						<result candidate_ref="3" vote="3" resp="Philip Lampi"/>
						<note resp="Philip Lampi">Peter S. Van Orden received 194 votes as Peter Van Orden.</note>
						<sub_unit type="Town" name="Amenia" geog_id="null">
							<result candidate_ref="1" vote="194" resp="Philip Lampi"/>
							<result candidate_ref="2" vote="149" resp="Philip Lampi"/>
						</sub_unit>
						<sub_unit type="Town" name="Beekman" geog_id="null">
							<result candidate_ref="1" vote="330" resp="Philip Lampi"/>
							<result candidate_ref="2" vote="75" resp="Philip Lampi"/>
						</sub_unit>
						<sub_unit type="Town" name="Clinton" geog_id="null">
							<result candidate_ref="1" vote="133" resp="Philip Lampi"/>
							<result candidate_ref="2" vote="172" resp="Philip Lampi"/>
						</sub_unit>
						<sub_unit type="Town" name="Dover" geog_id="null">
							<result candidate_ref="1" vote="205" resp="Philip Lampi"/>
							<result candidate_ref="2" vote="129" resp="Philip Lampi"/>
						</sub_unit>
						<sub_unit type="Town" name="Fishkill" geog_id="null">
							<result candidate_ref="1" vote="339" resp="Philip Lampi"/>
							<result candidate_ref="2" vote="520" resp="Philip Lampi"/>
						</sub_unit>
						<sub_unit type="Town" name="Freedom" geog_id="null">
							<result candidate_ref="1" vote="198" resp="Philip Lampi"/>
							<result candidate_ref="2" vote="113" resp="Philip Lampi"/>
						</sub_unit>
						<sub_unit type="Town" name="Hyde Park" geog_id="null">
							<result candidate_ref="1" vote="170" resp="Philip Lampi"/>
							<result candidate_ref="2" vote="146" resp="Philip Lampi"/>
						</sub_unit>
						<sub_unit type="Town" name="Milan" geog_id="null">
							<result candidate_ref="1" vote="88" resp="Philip Lampi"/>
							<result candidate_ref="2" vote="199" resp="Philip Lampi"/>
						</sub_unit>
						<sub_unit type="Town" name="Northeast" geog_id="null">
							<result candidate_ref="1" vote="104" resp="Philip Lampi"/>
							<result candidate_ref="2" vote="160" resp="Philip Lampi"/>
						</sub_unit>
						<sub_unit type="Town" name="Pawlings" geog_id="null">
							<result candidate_ref="1" vote="184" resp="Philip Lampi"/>
							<result candidate_ref="2" vote="84" resp="Philip Lampi"/>
						</sub_unit>
						<sub_unit type="Town" name="Pine Plains" geog_id="null">
							<result candidate_ref="1" vote="104" resp="Philip Lampi"/>
							<result candidate_ref="2" vote="153" resp="Philip Lampi"/>
						</sub_unit>
						<sub_unit type="Town" name="Pleasant Valley" geog_id="null">
							<result candidate_ref="1" vote="178" resp="Philip Lampi"/>
							<result candidate_ref="2" vote="165" resp="Philip Lampi"/>
						</sub_unit>
						<sub_unit type="Town" name="Poughkeepsie" geog_id="null">
							<result candidate_ref="1" vote="508" resp="Philip Lampi"/>
							<result candidate_ref="2" vote="377" resp="Philip Lampi"/>
						</sub_unit>
						<sub_unit type="Town" name="Red Hook" geog_id="null">
							<result candidate_ref="1" vote="226" resp="Philip Lampi"/>
							<result candidate_ref="2" vote="215" resp="Philip Lampi"/>
						</sub_unit>
						<sub_unit type="Town" name="Rhinebeck" geog_id="null">
							<result candidate_ref="1" vote="278" resp="Philip Lampi"/>
							<result candidate_ref="2" vote="240" resp="Philip Lampi"/>
						</sub_unit>
						<sub_unit type="Town" name="Stanford" geog_id="null">
							<result candidate_ref="1" vote="216" resp="Philip Lampi"/>
							<result candidate_ref="2" vote="146" resp="Philip Lampi"/>
						</sub_unit>
						<sub_unit type="Town" name="Washington" geog_id="null">
							<result candidate_ref="1" vote="191" resp="Philip Lampi"/>
							<result candidate_ref="2" vote="140" resp="Philip Lampi"/>
						</sub_unit>
					</sub_unit>
					<sub_unit type="County" name="Orange" geog_id="null">
						<result candidate_ref="1" vote="2212" resp="Philip Lampi"/>
						<result candidate_ref="2" vote="2187" resp="Philip Lampi"/>
						<result candidate_ref="3" vote="4" resp="Philip Lampi"/>
						<result candidate_ref="5" vote="1" resp="Philip Lampi"/>
						<result candidate_ref="13" vote="1" resp="Philip Lampi"/>
						<result candidate_ref="14" vote="1" resp="Philip Lampi"/>
						<result candidate_ref="15" vote="1" resp="Philip Lampi"/>
						<sub_unit type="Town" name="Blooming Grove" geog_id="null">
							<result candidate_ref="1" vote="126" resp="Philip Lampi"/>
							<result candidate_ref="2" vote="60" resp="Philip Lampi"/>
						</sub_unit>
						<sub_unit type="Town" name="Cornwall" geog_id="null">
							<result candidate_ref="1" vote="176" resp="Philip Lampi"/>
							<result candidate_ref="2" vote="35" resp="Philip Lampi"/>
						</sub_unit>
						<sub_unit type="Town" name="Crawford" geog_id="null">
							<result candidate_ref="1" vote="126" resp="Philip Lampi"/>
							<result candidate_ref="2" vote="134" resp="Philip Lampi"/>
						</sub_unit>
						<sub_unit type="Town" name="Deer Park" geog_id="null">
							<result candidate_ref="1" vote="53" resp="Philip Lampi"/>
							<result candidate_ref="2" vote="127" resp="Philip Lampi"/>
							<result candidate_ref="3" vote="1" resp="Philip Lampi"/>
						</sub_unit>
						<sub_unit type="Town" name="Goshen" geog_id="null">
							<result candidate_ref="1" vote="169" resp="Philip Lampi"/>
							<result candidate_ref="2" vote="245" resp="Philip Lampi"/>
							<result candidate_ref="3" vote="2" resp="Philip Lampi"/>
							<result candidate_ref="13" vote="1" resp="Philip Lampi"/>
							<result candidate_ref="14" vote="1" resp="Philip Lampi"/>
							<result candidate_ref="15" vote="1" resp="Philip Lampi"/>
						</sub_unit>
						<sub_unit type="Town" name="Minisink" geog_id="null">
							<result candidate_ref="1" vote="168" resp="Philip Lampi"/>
							<result candidate_ref="2" vote="381" resp="Philip Lampi"/>
						</sub_unit>
						<sub_unit type="Town" name="Monroe" geog_id="null">
							<result candidate_ref="1" vote="269" resp="Philip Lampi"/>
							<result candidate_ref="2" vote="75" resp="Philip Lampi"/>
						</sub_unit>
						<sub_unit type="Town" name="Montgomery" geog_id="null">
							<result candidate_ref="1" vote="247" resp="Philip Lampi"/>
							<result candidate_ref="2" vote="202" resp="Philip Lampi"/>
						</sub_unit>
						<sub_unit type="Town" name="New Windsor" geog_id="null">
							<result candidate_ref="1" vote="125" resp="Philip Lampi"/>
							<result candidate_ref="2" vote="103" resp="Philip Lampi"/>
						</sub_unit>
						<sub_unit type="Town" name="Newburgh" geog_id="null">
							<result candidate_ref="1" vote="224" resp="Philip Lampi"/>
							<result candidate_ref="2" vote="319" resp="Philip Lampi"/>
							<result candidate_ref="3" vote="1" resp="Philip Lampi"/>
							<result candidate_ref="5" vote="1" resp="Philip Lampi"/>
						</sub_unit>
						<sub_unit type="Town" name="Wallkill" geog_id="null">
							<result candidate_ref="1" vote="283" resp="Philip Lampi"/>
							<result candidate_ref="2" vote="321" resp="Philip Lampi"/>
						</sub_unit>
						<sub_unit type="Town" name="Warwick" geog_id="null">
							<result candidate_ref="1" vote="241" resp="Philip Lampi"/>
							<result candidate_ref="2" vote="185" resp="Philip Lampi"/>
						</sub_unit>
					</sub_unit>
					<sub_unit type="County" name="Putnam" geog_id="null">
						<result candidate_ref="1" vote="345" resp="Philip Lampi"/>
						<result candidate_ref="2" vote="798" resp="Philip Lampi"/>
						<result candidate_ref="3" vote="1" resp="Philip Lampi"/>
						<result candidate_ref="4" vote="3" resp="Philip Lampi"/>
						<result candidate_ref="6" vote="1" resp="Philip Lampi"/>
						<sub_unit type="Town" name="Carmel" geog_id="null">
							<result candidate_ref="1" vote="130" resp="Philip Lampi"/>
							<result candidate_ref="2" vote="203" resp="Philip Lampi"/>
						</sub_unit>
						<sub_unit type="Town" name="Kent" geog_id="null">
							<result candidate_ref="1" vote="15" resp="Philip Lampi"/>
							<result candidate_ref="2" vote="122" resp="Philip Lampi"/>
						</sub_unit>
						<sub_unit type="Town" name="Patterson" geog_id="null">
							<result candidate_ref="1" vote="77" resp="Philip Lampi"/>
							<result candidate_ref="2" vote="79" resp="Philip Lampi"/>
							<result candidate_ref="4" vote="1" resp="Philip Lampi"/>
							<result candidate_ref="6" vote="1" resp="Philip Lampi"/>
						</sub_unit>
						<sub_unit type="Town" name="Phillipstown" geog_id="null">
							<result candidate_ref="1" vote="60" resp="Philip Lampi"/>
							<result candidate_ref="2" vote="295" resp="Philip Lampi"/>
							<result candidate_ref="3" vote="3" resp="Philip Lampi"/>
						</sub_unit>
						<sub_unit type="Town" name="Southeast" geog_id="null">
							<result candidate_ref="1" vote="63" resp="Philip Lampi"/>
							<result candidate_ref="2" vote="99" resp="Philip Lampi"/>
						</sub_unit>
					</sub_unit>
					<sub_unit type="County" name="Rockland" geog_id="null">
						<result candidate_ref="1" vote="447" resp="Philip Lampi"/>
						<result candidate_ref="2" vote="419" resp="Philip Lampi"/>
						<reference type="page_image" urn="tufts:central:dca:MS115:MS115.001.DO.04733" resp="Philip Lampi"/>
						<sub_unit type="Town" name="Clarkstown" geog_id="null">
							<result candidate_ref="1" vote="67" resp="Philip Lampi"/>
							<result candidate_ref="2" vote="135" resp="Philip Lampi"/>
							<reference type="page_image" urn="tufts:central:dca:MS115:MS115.001.DO.04733" resp="Philip Lampi"/>
						</sub_unit>				
						<sub_unit type="Town" name="Haverstraw" geog_id="null">
							<result candidate_ref="1" vote="108" resp="Philip Lampi"/>
							<result candidate_ref="2" vote="92" resp="Philip Lampi"/>
							<reference type="page_image" urn="tufts:central:dca:MS115:MS115.001.DO.04733" resp="Philip Lampi"/>
						</sub_unit>
						<sub_unit type="Town" name="Hempstead" geog_id="null">
							<result candidate_ref="1" vote="236" resp="Philip Lampi"/>
							<result candidate_ref="2" vote="68" resp="Philip Lampi"/>
							<reference type="page_image" urn="tufts:central:dca:MS115:MS115.001.DO.04733" resp="Philip Lampi"/>
						</sub_unit>
						<sub_unit type="Town" name="Orangetown" geog_id="null">
							<result candidate_ref="1" vote="36" resp="Philip Lampi"/>
							<result candidate_ref="2" vote="124" resp="Philip Lampi"/>
							<reference type="page_image" urn="tufts:central:dca:MS115:MS115.001.DO.04733" resp="Philip Lampi"/>
						</sub_unit>
					</sub_unit>
					<sub_unit type="County" name="Sullivan" geog_id="null">
						<result candidate_ref="1" vote="507" resp="Philip Lampi"/>
						<result candidate_ref="2" vote="648" resp="Philip Lampi"/>
						<result candidate_ref="3" vote="3" resp="Philip Lampi"/>
						<reference type="page_image" urn="tufts:central:dca:MS115:MS115.001.DO.04739" resp="Philip Lampi"/>
					</sub_unit>
					<sub_unit type="County" name="Ulster" geog_id="null">
						<result candidate_ref="1" vote="2460" resp="Philip Lampi"/>
						<result candidate_ref="2" vote="2075" resp="Philip Lampi"/>
						<result candidate_ref="3" vote="1" resp="Philip Lampi"/>
						<result candidate_ref="7" vote="1" resp="Philip Lampi"/>
						<reference type="page_image" urn="tufts:central:dca:MS115:MS115.001.DO.04738" resp="Philip Lampi"/>
					</sub_unit>
					<sub_unit type="County" name="Westchester" geog_id="null">
						<result candidate_ref="1" vote="1394" resp="Philip Lampi"/>
						<result candidate_ref="2" vote="1749" resp="Philip Lampi"/>
						<result candidate_ref="8" vote="1" resp="Philip Lampi"/>
						<result candidate_ref="9" vote="1" resp="Philip Lampi"/>
						<result candidate_ref="10" vote="1" resp="Philip Lampi"/>
						<result candidate_ref="11" vote="1" resp="Philip Lampi"/>
						<result candidate_ref="12" vote="1" resp="Philip Lampi"/>
						<reference type="page_image" urn="tufts:central:dca:MS115:MS115.001.DO.04739" resp="Philip Lampi"/>
						<note resp="Philip Lampi">Peter S. Van Orden received 1 vote as Peter Van Ordern.</note>
						<note resp="Philip Lampi">Wells Lake received 4 vote as Wells Late.</note>
					</sub_unit>
				</sub_unit>
			</admin_unit>
		</role>
	</office>
	<reference type="citation" resp="Philip Lampi">The New-York Statesman (Albany, NY).  October 26, 1824.</reference>
	<reference type="citation" resp="Philip Lampi" urn="tufts:central:dca:MS115:MS115.001.DO.04732">The New-York Statesman (Albany, NY).  November 5, 1824.</reference>
	<reference type="citation" resp="Philip Lampi" urn="tufts:central:dca:MS115:MS115.001.DO.04733">National Advocate (New York, NY).  November 6, 1824.</reference>
	<reference type="citation" resp="Philip Lampi">Orange County Patriot; or, the Spirit of Seventy-Six (Goshen, NY).  November 15, 1824.</reference>
	<reference type="citation" resp="Philip Lampi" urn="tufts:central:dca:MS115:MS115.001.DO.04739">National Advocate (New York, NY).  November 19, 1824.</reference>
	<reference type="citation" resp="Philip Lampi" urn="tufts:central:dca:MS115:MS115.001.DO.04738">The Albany Argus (Albany, NY).  December 10, 1824.</reference>
	<reference type="citation" resp="Philip Lampi" urn="tufts:central:dca:MS115:MS115.001.DO.04738">The Albany Argus (Albany, NY).  December 14, 1824.</reference>
	<reference type="citation" resp="Philip Lampi" urn="tufts:central:dca:MS115:MS115.001.DO.04738">Original Manuscript of New York Assembly Elections.  Michael J. Dubin.</reference>
</election_record>
