<?xml version="1.0"?>
<election_record xmlns="http://dca.tufts.edu/aas" xmlns:xsi="http://www.w3.org/2001/XMLSchema-instance" label="New York 1808 Assembly, Jefferson County" type="General" iteration="First Ballot" date="1808" election_id="ny.assembly.jefferson.1808" handle="10427/25412" xsi:schemaLocation="http://dca.tufts.edu/aas http://dca.tufts.edu/schema/aas/electionRecord.xsd">
	<office name="Assembly" office_id="ON003" scope="State">
		<role title="Assemblyman" scope="County">
			<ballot>
				<candidate name="Corlis Hinds" name_id="HC0066" affiliation="Republican" affiliation_id="A03" candidate_num="1"><note resp="Philip Lampi">Elected.</note></candidate>
				<candidate name="David Ira Andrus" name_id="AD0014" affiliation="Republican" affiliation_id="A03" candidate_num="2"><note resp="Philip Lampi">Elected.</note></candidate>
				<candidate name="Ethel Bronson" name_id="BE0228" affiliation="Federalist" affiliation_id="A01" candidate_num="3"/>
				<candidate name="Jesse Hopkins" name_id="HJ0545" affiliation="Federalist" affiliation_id="A01" candidate_num="4"/>
				<candidate name="Joshua Beals" name_id="BJ0548" affiliation="null" affiliation_id="null" candidate_num="5"/>
				<candidate name="George Hopkins" name_id="HG0113" affiliation="null" affiliation_id="null" candidate_num="6"/>
				<candidate name="John Nicholson" name_id="NJ0071" affiliation="null" affiliation_id="null" candidate_num="7"/>
				<candidate name="Roswell Hopkins" name_id="HR0129" affiliation="null" affiliation_id="null" candidate_num="8"/>
				<candidate name="Jesse Bronson" name_id="BJ0615" affiliation="null" affiliation_id="null" candidate_num="9"/>
				<candidate name="Samuel S. Forman" name_id="FS0076" affiliation="null" affiliation_id="null" candidate_num="10"/>
				<candidate name="Martin Gaylord" name_id="GM0011" affiliation="null" affiliation_id="null" candidate_num="11"/>
				<candidate name="Francis Henry" name_id="HF0029" affiliation="null" affiliation_id="null" candidate_num="12"/>
				<candidate name="Henry MacNeil" name_id="MH0068" affiliation="null" affiliation_id="null" candidate_num="13"/>
				<candidate name="Wilhelmus Wynderse" name_id="MW0216" affiliation="null" affiliation_id="null" candidate_num="14"/>
				<candidate name="Luther Hinds" name_id="HL0047" affiliation="null" affiliation_id="null" candidate_num="15"/>
				<candidate name="William Hunter" name_id="HW0221" affiliation="null" affiliation_id="null" candidate_num="16"/>
				<candidate name="Silas Hinds" name_id="HS0143" affiliation="null" affiliation_id="null" candidate_num="17"/>
				<candidate name="Elias Skinner" name_id="SE0136" affiliation="null" affiliation_id="null" candidate_num="18"/>
				<candidate name="Asa Bronson" name_id="BA0131" affiliation="null" affiliation_id="null" candidate_num="19"/>
			</ballot>
			<overview status="Version 0.5" modified="2014-01-10">
				<candidate_summary candidate_ref="1" vote_total="767" resp="Philip Lampi"/>
				<candidate_summary candidate_ref="2" vote_total="686" resp="Philip Lampi"/>
				<candidate_summary candidate_ref="3" vote_total="596" resp="Philip Lampi"/>
				<candidate_summary candidate_ref="4" vote_total="535" resp="Philip Lampi"/>
				<candidate_summary candidate_ref="5" vote_total="4" resp="Philip Lampi"/>
				<candidate_summary candidate_ref="6" vote_total="4" resp="Philip Lampi"/>
				<candidate_summary candidate_ref="7" vote_total="3" resp="Philip Lampi"/>
				<candidate_summary candidate_ref="8" vote_total="2" resp="Philip Lampi"/>
				<candidate_summary candidate_ref="9" vote_total="1" resp="Philip Lampi"/>
				<candidate_summary candidate_ref="10" vote_total="1" resp="Philip Lampi"/>
				<candidate_summary candidate_ref="11" vote_total="1" resp="Philip Lampi"/>
				<candidate_summary candidate_ref="12" vote_total="1" resp="Philip Lampi"/>
				<candidate_summary candidate_ref="13" vote_total="1" resp="Philip Lampi"/>
				<candidate_summary candidate_ref="14" vote_total="1" resp="Philip Lampi"/>
				<candidate_summary candidate_ref="15" vote_total="1" resp="Philip Lampi"/>
				<candidate_summary candidate_ref="16" vote_total="1" resp="Philip Lampi"/>
				<candidate_summary candidate_ref="17" vote_total="1" resp="Philip Lampi"/>
				<candidate_summary candidate_ref="18" vote_total="1" resp="Philip Lampi"/>
				<candidate_summary candidate_ref="19" vote_total="1" resp="Philip Lampi"/>
				<reference type="page_image" urn="tufts:central:dca:MS115:MS115.001.DO.04321" resp="Philip Lampi"/>
				<note resp="Philip Lampi">The Columbian Gazette (Utica, NY) reports 536 votes for Jesse Hopkins in Jefferson County.</note>
				<note resp="Philip Lampi">Rosewell Hopkins, Henry McNeil, Francis Henry, Samuel S. Forman, and Wilhelmus Mynderse were candidates for State Senate.</note>
			</overview>
			<admin_unit type="State" name="New York" geog_id="null">
				<sub_unit type="County" name="Jefferson" geog_id="null">
					<result candidate_ref="1" vote="767" resp="Philip Lampi"/>
					<result candidate_ref="2" vote="686" resp="Philip Lampi"/>
					<result candidate_ref="3" vote="596" resp="Philip Lampi"/>
					<result candidate_ref="4" vote="535" resp="Philip Lampi"/>
					<result candidate_ref="5" vote="4" resp="Philip Lampi"/>
					<result candidate_ref="6" vote="4" resp="Philip Lampi"/>
					<result candidate_ref="7" vote="3" resp="Philip Lampi"/>
					<result candidate_ref="8" vote="2" resp="Philip Lampi"/>
					<result candidate_ref="9" vote="1" resp="Philip Lampi"/>
					<result candidate_ref="10" vote="1" resp="Philip Lampi"/>
					<result candidate_ref="11" vote="1" resp="Philip Lampi"/>
					<result candidate_ref="12" vote="1" resp="Philip Lampi"/>
					<result candidate_ref="13" vote="1" resp="Philip Lampi"/>
					<result candidate_ref="14" vote="1" resp="Philip Lampi"/>
					<result candidate_ref="15" vote="1" resp="Philip Lampi"/>
					<result candidate_ref="16" vote="1" resp="Philip Lampi"/>
					<result candidate_ref="17" vote="1" resp="Philip Lampi"/>
					<result candidate_ref="18" vote="1" resp="Philip Lampi"/>
					<result candidate_ref="19" vote="1" resp="Philip Lampi"/>
					<reference type="page_image" urn="tufts:central:dca:MS115:MS115.001.DO.04321" resp="Philip Lampi"/>
					<sub_unit type="Town" name="Adams" geog_id="null">
						<result candidate_ref="1" vote="54" resp="Philip Lampi"/>
						<result candidate_ref="2" vote="52" resp="Philip Lampi"/>
						<result candidate_ref="3" vote="52" resp="Philip Lampi"/>
						<result candidate_ref="4" vote="50" resp="Philip Lampi"/>
						<result candidate_ref="7" vote="1" resp="Philip Lampi"/>
						<result candidate_ref="8" vote="1" resp="Philip Lampi"/>
						<result candidate_ref="9" vote="1" resp="Philip Lampi"/>
						<result candidate_ref="10" vote="1" resp="Philip Lampi"/>
						<result candidate_ref="11" vote="1" resp="Philip Lampi"/>
						<result candidate_ref="12" vote="1" resp="Philip Lampi"/>
						<result candidate_ref="13" vote="1" resp="Philip Lampi"/>
						<result candidate_ref="14" vote="1" resp="Philip Lampi"/>
					</sub_unit>
					<sub_unit type="Town" name="Brownville" geog_id="null">
						<result candidate_ref="1" vote="90" resp="Philip Lampi"/>
						<result candidate_ref="2" vote="86" resp="Philip Lampi"/>
						<result candidate_ref="3" vote="49" resp="Philip Lampi"/>
						<result candidate_ref="4" vote="46" resp="Philip Lampi"/>
					</sub_unit>
					<sub_unit type="Town" name="Champion" geog_id="null">
						<result candidate_ref="1" vote="35" resp="Philip Lampi"/>
						<result candidate_ref="2" vote="36" resp="Philip Lampi"/>
						<result candidate_ref="3" vote="99" resp="Philip Lampi"/>
						<result candidate_ref="4" vote="99" resp="Philip Lampi"/>
						<result candidate_ref="15" vote="1" resp="Philip Lampi"/>
					</sub_unit>
					<sub_unit type="Town" name="Ellisburgh" geog_id="null">
						<result candidate_ref="1" vote="117" resp="Philip Lampi"/>
						<result candidate_ref="2" vote="106" resp="Philip Lampi"/>
						<result candidate_ref="3" vote="26" resp="Philip Lampi"/>
						<result candidate_ref="4" vote="28" resp="Philip Lampi"/>
						<result candidate_ref="5" vote="2" resp="Philip Lampi"/>
						<result candidate_ref="16" vote="1" resp="Philip Lampi"/>
					</sub_unit>
					<sub_unit type="Town" name="Harrison" geog_id="null">
						<result candidate_ref="1" vote="73" resp="Philip Lampi"/>
						<result candidate_ref="2" vote="62" resp="Philip Lampi"/>
						<result candidate_ref="3" vote="72" resp="Philip Lampi"/>
						<result candidate_ref="4" vote="61" resp="Philip Lampi"/>
					</sub_unit>
					<sub_unit type="Town" name="Henderson" geog_id="null">
						<result candidate_ref="1" vote="41" resp="Philip Lampi"/>
						<result candidate_ref="2" vote="39" resp="Philip Lampi"/>
						<result candidate_ref="3" vote="35" resp="Philip Lampi"/>
						<result candidate_ref="4" vote="35" resp="Philip Lampi"/>
						<result candidate_ref="5" vote="2" resp="Philip Lampi"/>
						<result candidate_ref="17" vote="1" resp="Philip Lampi"/>
						<result candidate_ref="18" vote="1" resp="Philip Lampi"/>
					</sub_unit>
					<sub_unit type="Town" name="Houndsfield" geog_id="null">
						<result candidate_ref="1" vote="58" resp="Philip Lampi"/>
						<result candidate_ref="2" vote="38" resp="Philip Lampi"/>
						<result candidate_ref="3" vote="37" resp="Philip Lampi"/>
						<result candidate_ref="4" vote="17" resp="Philip Lampi"/>
					</sub_unit>
					<sub_unit type="Town" name="LeRay" geog_id="null">
						<result candidate_ref="1" vote="43" resp="Philip Lampi"/>
						<result candidate_ref="2" vote="43" resp="Philip Lampi"/>
						<result candidate_ref="3" vote="18" resp="Philip Lampi"/>
						<result candidate_ref="4" vote="11" resp="Philip Lampi"/>
						<result candidate_ref="6" vote="4" resp="Philip Lampi"/>
						<result candidate_ref="7" vote="2" resp="Philip Lampi"/>
						<note resp="Philip Lampi">David Ira Andrus received 13 votes as Daniel I. Andrus.</note>
					</sub_unit>
					<sub_unit type="Town" name="Malta" geog_id="null">
						<result candidate_ref="1" vote="35" resp="Philip Lampi"/>
						<result candidate_ref="2" vote="34" resp="Philip Lampi"/>
						<result candidate_ref="3" vote="50" resp="Philip Lampi"/>
						<result candidate_ref="4" vote="54" resp="Philip Lampi"/>
						<note resp="Philip Lampi">David Ira Andrus received 1 vote as David Andrus.</note>
					</sub_unit>
					<sub_unit type="Town" name="Rutland" geog_id="null">
						<result candidate_ref="1" vote="122" resp="Philip Lampi"/>
						<result candidate_ref="2" vote="113" resp="Philip Lampi"/>
						<result candidate_ref="3" vote="62" resp="Philip Lampi"/>
						<result candidate_ref="4" vote="45" resp="Philip Lampi"/>
					</sub_unit>
					<sub_unit type="Town" name="Watertown" geog_id="null">
						<result candidate_ref="1" vote="99" resp="Philip Lampi"/>
						<result candidate_ref="2" vote="91" resp="Philip Lampi"/>
						<result candidate_ref="3" vote="96" resp="Philip Lampi"/>
						<result candidate_ref="4" vote="89" resp="Philip Lampi"/>
						<result candidate_ref="8" vote="1" resp="Philip Lampi"/>
						<result candidate_ref="19" vote="1" resp="Philip Lampi"/>
					</sub_unit>
				</sub_unit>
			</admin_unit>
		</role>
	</office>
	<reference type="citation" resp="Philip Lampi">Original Election Books.</reference>
	<reference type="citation" resp="Philip Lampi" urn="tufts:central:dca:MS115:MS115.001.DO.04321">Columbian Gazette (Utica, NY).  May 17, 1808.</reference>
</election_record>
