<?xml version="1.0"?>
<election_record xmlns="http://dca.tufts.edu/aas" xmlns:xsi="http://www.w3.org/2001/XMLSchema-instance" label="Maryland 1816 House of Delegates, Harford County" type="General" iteration="First Ballot" date="1816" election_id="md.assembly.harford.county.1816" handle="10427/26511" xsi:schemaLocation="http://dca.tufts.edu/aas http://dca.tufts.edu/schema/aas/electionRecord.xsd">
	<office name="House of Delegates" office_id="ON063" scope="State">
		<role title="Delegate" scope="County">
			<ballot>
				<candidate name="Charles S. Sewall" name_id="SC0014" affiliation="Republican" affiliation_id="A03" candidate_num="1"/>
				<candidate name="Henry Hall" name_id="HH0022" affiliation="Republican" affiliation_id="A03" candidate_num="2"/>
				<candidate name="Samuel Bradford" name_id="BS0079" affiliation="Republican" affiliation_id="A03" candidate_num="3"/>
				<candidate name="John Glenn" name_id="GJ0135" affiliation="Republican" affiliation_id="A03" candidate_num="4"/>
				<candidate name="James Wallace" name_id="WJ0191" affiliation="null" affiliation_id="null" candidate_num="5"/>
				<candidate name="Henry Macater" name_id="MH0009" affiliation="null" affiliation_id="null" candidate_num="6"/>
				<candidate name="Samuel Harper" name_id="HS0076" affiliation="null" affiliation_id="null" candidate_num="7"/>
				<candidate name="George Presbury" name_id="PG0079" affiliation="null" affiliation_id="null" candidate_num="8"/>
				<candidate name="John G. Grindell" name_id="GJ0127" affiliation="null" affiliation_id="null" candidate_num="9"/>
				<candidate name="John MacComas" name_id="MJ0063" affiliation="null" affiliation_id="null" candidate_num="10"/>
				<candidate name="Thomas Jeffery" name_id="JT0011" affiliation="null" affiliation_id="null" candidate_num="11"/>
				<candidate name="John Watson" name_id="WJ0979" affiliation="null" affiliation_id="null" candidate_num="12"/>
				<candidate name="William Mills" name_id="MW0030" affiliation="null" affiliation_id="null" candidate_num="13"/>
				<candidate name="Abel Anderson" name_id="AA0038" affiliation="null" affiliation_id="null" candidate_num="14"/>
				<candidate name="Thomas Bond" name_id="BT0101" affiliation="null" affiliation_id="null" candidate_num="15"/>
				<candidate name="John Morris" name_id="MJ0064" affiliation="null" affiliation_id="null" candidate_num="16"/>
				<candidate name="Joseph Brownley" name_id="BJ0442" affiliation="null" affiliation_id="null" candidate_num="17"/>
				<candidate name="James Steele" name_id="SJ0310" affiliation="null" affiliation_id="null" candidate_num="18"/>
				<candidate name="Thomas Morford" name_id="MT0002" affiliation="null" affiliation_id="null" candidate_num="19"/>
			</ballot>
			<overview status="Version 1.0" modified="2008-07-01">
				<candidate_summary candidate_ref="1" vote_total="1136" resp="Philip Lampi"/>
				<candidate_summary candidate_ref="2" vote_total="1110" resp="Philip Lampi"/>
				<candidate_summary candidate_ref="3" vote_total="1106" resp="Philip Lampi"/>
				<candidate_summary candidate_ref="4" vote_total="944" resp="Philip Lampi"/>
				<candidate_summary candidate_ref="5" vote_total="622" resp="Philip Lampi"/>
				<candidate_summary candidate_ref="6" vote_total="471" resp="Philip Lampi"/>
				<candidate_summary candidate_ref="7" vote_total="319" resp="Philip Lampi"/>
				<candidate_summary candidate_ref="8" vote_total="11" resp="Philip Lampi"/>
				<candidate_summary candidate_ref="9" vote_total="2" resp="Philip Lampi"/>
				<candidate_summary candidate_ref="10" vote_total="1" resp="Philip Lampi"/>
				<candidate_summary candidate_ref="11" vote_total="1" resp="Philip Lampi"/>
				<candidate_summary candidate_ref="12" vote_total="1" resp="Philip Lampi"/>
				<candidate_summary candidate_ref="13" vote_total="1" resp="Philip Lampi"/>
				<candidate_summary candidate_ref="14" vote_total="1" resp="Philip Lampi"/>
				<candidate_summary candidate_ref="15" vote_total="1" resp="Philip Lampi"/>
				<candidate_summary candidate_ref="16" vote_total="1" resp="Philip Lampi"/>
				<candidate_summary candidate_ref="17" vote_total="1" resp="Philip Lampi"/>
				<candidate_summary candidate_ref="18" vote_total="1" resp="Philip Lampi"/>
				<candidate_summary candidate_ref="19" vote_total="1" resp="Philip Lampi"/>
				<reference type="page_image" urn="tufts:central:dca:MS115:MS115.001.DO.02996" resp="Philip Lampi"/>
				<reference type="page_image" urn="tufts:central:dca:MS115:MS115.001.DO.14739" resp="Philip Lampi"/>
				<note resp="Philip Lampi">John G. Grindell is also listed as John G. Grindale.</note>
			</overview>
			<admin_unit type="State" name="Maryland" geog_id="mds">
				<sub_unit type="County" name="Harford" geog_id="mds_harford">
					<result candidate_ref="1" vote="1136" resp="Philip Lampi"/>
					<result candidate_ref="2" vote="1110" resp="Philip Lampi"/>
					<result candidate_ref="3" vote="1106" resp="Philip Lampi"/>
					<result candidate_ref="4" vote="944" resp="Philip Lampi"/>
					<result candidate_ref="5" vote="622" resp="Philip Lampi"/>
					<result candidate_ref="6" vote="471" resp="Philip Lampi"/>
					<result candidate_ref="7" vote="319" resp="Philip Lampi"/>
					<result candidate_ref="8" vote="11" resp="Philip Lampi"/>
					<result candidate_ref="9" vote="2" resp="Philip Lampi"/>
					<result candidate_ref="10" vote="1" resp="Philip Lampi"/>
					<result candidate_ref="11" vote="1" resp="Philip Lampi"/>
					<result candidate_ref="12" vote="1" resp="Philip Lampi"/>
					<result candidate_ref="13" vote="1" resp="Philip Lampi"/>
					<result candidate_ref="14" vote="1" resp="Philip Lampi"/>
					<result candidate_ref="15" vote="1" resp="Philip Lampi"/>
					<result candidate_ref="16" vote="1" resp="Philip Lampi"/>
					<result candidate_ref="17" vote="1" resp="Philip Lampi"/>
					<result candidate_ref="18" vote="1" resp="Philip Lampi"/>
					<result candidate_ref="19" vote="1" resp="Philip Lampi"/>
					<sub_unit type="Town" name="Abingdon" geog_id="null">
						<result candidate_ref="1" vote="187" resp="Philip Lampi"/>
						<result candidate_ref="2" vote="166" resp="Philip Lampi"/>
						<result candidate_ref="3" vote="160" resp="Philip Lampi"/>
						<result candidate_ref="4" vote="126" resp="Philip Lampi"/>
						<result candidate_ref="5" vote="80" resp="Philip Lampi"/>
						<result candidate_ref="6" vote="37" resp="Philip Lampi"/>
						<result candidate_ref="7" vote="15" resp="Philip Lampi"/>
						<result candidate_ref="8" vote="11" resp="Philip Lampi"/>
						<result candidate_ref="10" vote="1" resp="Philip Lampi"/>
						<reference type="page_image" urn="tufts:central:dca:MS115:MS115.001.DO.14739" resp="Philip Lampi"/>
						<note resp="Philip Lampi">This was also known as District No. 1.</note>
					</sub_unit>
					<sub_unit type="Town" name="Bel Air" geog_id="null">
						<result candidate_ref="1" vote="234" resp="Philip Lampi"/>
						<result candidate_ref="2" vote="221" resp="Philip Lampi"/>
						<result candidate_ref="3" vote="238" resp="Philip Lampi"/>
						<result candidate_ref="4" vote="179" resp="Philip Lampi"/>
						<result candidate_ref="5" vote="190" resp="Philip Lampi"/>
						<result candidate_ref="6" vote="158" resp="Philip Lampi"/>
						<result candidate_ref="7" vote="79" resp="Philip Lampi"/>
						<result candidate_ref="9" vote="2" resp="Philip Lampi"/>
						<result candidate_ref="12" vote="1" resp="Philip Lampi"/>
						<result candidate_ref="13" vote="1" resp="Philip Lampi"/>
						<result candidate_ref="19" vote="1" resp="Philip Lampi"/>
						<reference type="page_image" urn="tufts:central:dca:MS115:MS115.001.DO.14739" resp="Philip Lampi"/>
						<note resp="Philip Lampi">This was also known as District No. 3.</note>
					</sub_unit>
					<sub_unit type="Town" name="Dublin" geog_id="null">
						<result candidate_ref="1" vote="254" resp="Philip Lampi"/>
						<result candidate_ref="2" vote="253" resp="Philip Lampi"/>
						<result candidate_ref="3" vote="250" resp="Philip Lampi"/>
						<result candidate_ref="4" vote="208" resp="Philip Lampi"/>
						<result candidate_ref="5" vote="89" resp="Philip Lampi"/>
						<result candidate_ref="6" vote="97" resp="Philip Lampi"/>
						<result candidate_ref="7" vote="45" resp="Philip Lampi"/>
						<result candidate_ref="16" vote="1" resp="Philip Lampi"/>
						<result candidate_ref="17" vote="1" resp="Philip Lampi"/>
						<result candidate_ref="18" vote="1" resp="Philip Lampi"/>
						<reference type="page_image" urn="tufts:central:dca:MS115:MS115.001.DO.14739" resp="Philip Lampi"/>
						<note resp="Philip Lampi">This was also known as District No. 5.</note>
					</sub_unit>
					<sub_unit type="Populated Place" name="Hall's Cross Roads" geog_id="null">
						<result candidate_ref="1" vote="340" resp="Philip Lampi"/>
						<result candidate_ref="2" vote="341" resp="Philip Lampi"/>
						<result candidate_ref="3" vote="313" resp="Philip Lampi"/>
						<result candidate_ref="4" vote="287" resp="Philip Lampi"/>
						<result candidate_ref="5" vote="80" resp="Philip Lampi"/>
						<result candidate_ref="6" vote="56" resp="Philip Lampi"/>
						<result candidate_ref="7" vote="4" resp="Philip Lampi"/>
						<result candidate_ref="11" vote="1" resp="Philip Lampi"/>
						<reference type="page_image" urn="tufts:central:dca:MS115:MS115.001.DO.14739" resp="Philip Lampi"/>
						<note resp="Philip Lampi">This was also known as District No. 2.</note>
					</sub_unit>
					<sub_unit type="Populated Place" name="Marshall's" geog_id="null">
						<result candidate_ref="1" vote="121" resp="Philip Lampi"/>
						<result candidate_ref="2" vote="129" resp="Philip Lampi"/>
						<result candidate_ref="3" vote="145" resp="Philip Lampi"/>
						<result candidate_ref="4" vote="144" resp="Philip Lampi"/>
						<result candidate_ref="5" vote="183" resp="Philip Lampi"/>
						<result candidate_ref="6" vote="123" resp="Philip Lampi"/>
						<result candidate_ref="7" vote="176" resp="Philip Lampi"/>
						<result candidate_ref="14" vote="1" resp="Philip Lampi"/>
						<result candidate_ref="15" vote="1" resp="Philip Lampi"/>
						<reference type="page_image" urn="tufts:central:dca:MS115:MS115.001.DO.14739" resp="Philip Lampi"/>
						<note resp="Philip Lampi">This was also known as District No. 4.</note>
					</sub_unit>
				</sub_unit>
			</admin_unit>
		</role>
	</office>
	<reference type="citation" resp="Philip Lampi" urn="tufts:central:dca:MS115:MS115.001.DO.02996">Original Election Returns.  Maryland State Archives, Annapolis.</reference>
	<reference type="citation" resp="Philip Lampi" urn="tufts:central:dca:MS115:MS115.001.DO.14739">Election Transcript.  Historical Society of Harford County, Bel Air.</reference>
</election_record>
