<?xml version="1.0"?>
<election_record xmlns="http://dca.tufts.edu/aas" xmlns:xsi="http://www.w3.org/2001/XMLSchema-instance" label="Pennsylvania 1821 Speaker of the House" type="Legislative" iteration="First Ballot" date="1821-12" election_id="pa.speakerofthehouse.1821" handle="10427/63542" xsi:schemaLocation="http://dca.tufts.edu/aas http://dca.tufts.edu/schema/aas/electionRecord.xsd">
	<office name="Speaker of the House" office_id="ON104" scope="State">
		<role title="Speaker of the House" scope="State">
			<ballot>
				<candidate name="Joseph Lawrence" name_id="LJ0456" affiliation="null" affiliation_id="null" candidate_num="1"><note resp="Philip Lampi">Elected.</note></candidate>
				<candidate name="William Lehman" name_id="LW0199" affiliation="null" affiliation_id="null" candidate_num="2"/>
				<candidate name="Jacob Casset" name_id="CJ0774" affiliation="null" affiliation_id="null" candidate_num="3"/>
				<candidate name="Jacob Holgate" name_id="HJ0818" affiliation="null" affiliation_id="null" candidate_num="4"/>
				<candidate name="James Todd" name_id="TJ0523" affiliation="null" affiliation_id="null" candidate_num="5"/>
			</ballot>
			<overview status="Version 0.5" modified="2013-07-15">
				<candidate_summary candidate_ref="1" vote_total="69" resp="Philip Lampi"/>
				<candidate_summary candidate_ref="2" vote_total="18" resp="Philip Lampi"/>
				<candidate_summary candidate_ref="3" vote_total="1" resp="Philip Lampi"/>
				<candidate_summary candidate_ref="4" vote_total="1" resp="Philip Lampi"/>
				<candidate_summary candidate_ref="5" vote_total="1" resp="Philip Lampi"/>
				<reference type="page_image" urn="tufts:central:dca:MS115:MS115.001.DO.10849" resp="Philip Lampi"/>
				<reference type="page_image" urn="tufts:central:dca:MS115:MS115.001.DO.10850" resp="Philip Lampi"/>
				<reference type="page_image" urn="tufts:central:dca:MS115:MS115.001.DO.10851" resp="Philip Lampi"/>
				<reference type="page_image" urn="tufts:central:dca:MS115:MS115.001.DO.10852" resp="Philip Lampi"/>
				<note resp="Philip Lampi">"In the house of representatives on Tuesday afternoon, 90 members, 5 republicans and 2 federalist absent."  Franklin Gazette (for the Country) (Philadelphia, PA).  December 12, 1821.</note>
				<note resp="Philip Lampi">The vote for Jacob Holgate was cast by "Mr. Lawrence," and the vote for James Todd was cast by "Mr. Stockman."</note>
			</overview>
			<admin_unit type="State" name="Pennsylvania" geog_id="null">
				<sub_unit type="null" name="House of Representatives" geog_id="null">
					<result candidate_ref="1" vote="69" resp="Philip Lampi"/>
					<result candidate_ref="2" vote="18" resp="Philip Lampi"/>
					<result candidate_ref="3" vote="1" resp="Philip Lampi"/>
					<result candidate_ref="4" vote="1" resp="Philip Lampi"/>
					<result candidate_ref="5" vote="1" resp="Philip Lampi"/>
					<reference type="page_image" urn="tufts:central:dca:MS115:MS115.001.DO.10849" resp="Philip Lampi"/>
					<reference type="page_image" urn="tufts:central:dca:MS115:MS115.001.DO.10850" resp="Philip Lampi"/>
					<reference type="page_image" urn="tufts:central:dca:MS115:MS115.001.DO.10851" resp="Philip Lampi"/>
					<reference type="page_image" urn="tufts:central:dca:MS115:MS115.001.DO.10852" resp="Philip Lampi"/>
				</sub_unit>
			</admin_unit>
		</role>
	</office>
	<reference type="citation" resp="Philip Lampi" urn="tufts:central:dca:MS115:MS115.001.DO.10849">Franklin Gazette (for the Country) (Philadelphia, PA).  December 12, 1821.</reference>
	<reference type="citation" resp="Philip Lampi" urn="tufts:central:dca:MS115:MS115.001.DO.10850">The Westmoreland Republican (Greensburgh, PA).  December 14, 1821.</reference>
	<reference type="citation" resp="Philip Lampi" urn="tufts:central:dca:MS115:MS115.001.DO.10852">Nordwestliche Post (Sunbury, PA).  December 21, 1820.</reference>
	<reference type="citation" resp="Philip Lampi" urn="tufts:central:dca:MS115:MS115.001.DO.10851">Erie Gazette (Erie, PA).  December 22, 1820.</reference>
</election_record>
